rossmann_appearance_analyzer/__init__.py
rossmann_appearance_analyzer/main.py
rossmann_appearance_analyzer/prompts.py
rossmann_appearance_analyzer-2025.12.21113604.dist-info/METADATA
rossmann_appearance_analyzer-2025.12.21113604.dist-info/WHEEL
rossmann_appearance_analyzer-2025.12.21113604.dist-info/top_level.txt
rossmann_appearance_analyzer-2025.12.21113604.dist-info/RECORD
