Metadata-Version: 2.4
Name: rossmann-appearance-analyzer
Version: 2025.12.21113604
Summary: A new package is designed to analyze user inputs related to avoiding negative or unwelcome appearances on a Louis Rossmann video. It processes the text input to identify key factors or common pitfalls
Author-email: rossmann-appearance-analyzer <hi@eugene.plus>
License: MIT
Project-URL: Homepage, https://github.com/chigwell/rossmann-appearance-analyzer
Requires-Python: >=3.9
Requires-Dist: langchain-llm7>=0.0.0
Requires-Dist: llmatch-messages>=0.0.0
Requires-Dist: langchain-core>=0.3.0
